bounded_executor/__init__.py
bounded_executor/executors.py
bounded_executor-0.0.5.dist-info/METADATA
bounded_executor-0.0.5.dist-info/WHEEL
bounded_executor-0.0.5.dist-info/top_level.txt
bounded_executor-0.0.5.dist-info/RECORD
